README.md
setup.cfg
setup.py
cmd_line/__init__.py
cmd_line/seins_cmd.py
seins/HtmlFetcher.py
seins/PageParser.py
seins/__init__.py
seins.egg-info/PKG-INFO
seins.egg-info/SOURCES.txt
seins.egg-info/dependency_links.txt
seins.egg-info/entry_points.txt
seins.egg-info/requires.txt
seins.egg-info/top_level.txt