Metadata-Version: 1.1
Name: seins
Version: 0.3.2
Summary: A  small module and  command line utility to show you when the next train to your desired location is arriving by parsing the DB website
Home-page: https://github.com/kbruegge/sEins-Server
Author: Kai
Author-email: kai@woistbier.de
License: MIT
Download-URL: https://github.com/kbruegge/sEins-Server/archive/master.zip
Keywords: traffic,scrapping,utility,transportation,s1,DB
Platform: UNKNOWN
Classifier: Development Status :: 3 - Alpha
Classifier: Topic :: Utilities
Classifier: License :: OSI Approved :: MIT License
Classifier: Programming Language :: Python :: 3
